{"@timestamp":"2026-01-04T00:17:23.0681838+06:00","@version":"1","message":"Parsed arguments: email=a***@yopmail.com, org=Demo, env=CRUDTest, browser=api, headless=false","logger_name":"com.selise.inb.automation.auth.AutomationArgumentParser","thread_name":"main","level":"INFO","level_value":20000,"application":"selise-automation"}
{"@timestamp":"2026-01-04T00:17:23.1618916+06:00","@version":"1","message":"Delegating to BackendAutomationRunner for API automation","logger_name":"com.selise.inb.application.InbAutomationApp","thread_name":"main","level":"INFO","level_value":20000,"application":"selise-automation"}
{"@timestamp":"2026-01-04T00:17:23.1648761+06:00","@version":"1","message":"Parsed arguments: email=a***@yopmail.com, org=Demo, env=CRUDTest, browser=api, headless=false","logger_name":"com.selise.inb.automation.auth.AutomationArgumentParser","thread_name":"main","level":"INFO","level_value":20000,"application":"selise-automation"}
{"@timestamp":"2026-01-04T00:17:23.1668789+06:00","@version":"1","message":"Backend Automation Started with environment: CRUDTest","logger_name":"com.selise.inb.application.BackendAutomationRunner","thread_name":"main","level":"INFO","level_value":20000,"application":"selise-automation"}
{"@timestamp":"2026-01-04T00:17:23.404798+06:00","@version":"1","message":"Instance configuration loaded successfully.","logger_name":"com.selise.inb.automation.config.ConfigurationManager","thread_name":"main","level":"INFO","level_value":20000,"application":"selise-automation"}
{"@timestamp":"2026-01-04T00:17:23.4071875+06:00","@version":"1","message":"Authenticating user: a***@yopmail.com","logger_name":"com.selise.inb.automation.auth.AuthenticationHelper","thread_name":"main","level":"INFO","level_value":20000,"application":"selise-automation"}
{"@timestamp":"2026-01-04T00:17:23.4140733+06:00","@version":"1","message":"Authenticating user: a***@yopmail.com","logger_name":"com.selise.inb.automation.auth.IdentityServiceClient","thread_name":"main","level":"INFO","level_value":20000,"application":"selise-automation"}
{"@timestamp":"2026-01-04T00:17:24.8981165+06:00","@version":"1","message":"✓ Authentication successful","logger_name":"com.selise.inb.automation.auth.IdentityServiceClient","thread_name":"main","level":"INFO","level_value":20000,"application":"selise-automation"}
{"@timestamp":"2026-01-04T00:17:24.9001002+06:00","@version":"1","message":"Retrieving user context...","logger_name":"com.selise.inb.automation.auth.IdentityServiceClient","thread_name":"main","level":"INFO","level_value":20000,"application":"selise-automation"}
{"@timestamp":"2026-01-04T00:17:25.1781759+06:00","@version":"1","message":"✓ User context retrieved: 3 organization(s) accessible","logger_name":"com.selise.inb.automation.auth.IdentityServiceClient","thread_name":"main","level":"INFO","level_value":20000,"application":"selise-automation"}
{"@timestamp":"2026-01-04T00:17:25.1821871+06:00","@version":"1","message":"Organization specified: Demo","logger_name":"com.selise.inb.automation.auth.OrganizationSelector","thread_name":"main","level":"INFO","level_value":20000,"application":"selise-automation"}
{"@timestamp":"2026-01-04T00:17:25.1852832+06:00","@version":"1","message":"✓ Organization validated by name: Demo (c3c8a454-9530-41ba-8a43-c4cbd0308fbc)","logger_name":"com.selise.inb.automation.auth.OrganizationSelector","thread_name":"main","level":"INFO","level_value":20000,"application":"selise-automation"}
{"@timestamp":"2026-01-04T00:17:25.1941895+06:00","@version":"1","message":"Selected organization: Demo (c3c8a454-9530-41ba-8a43-c4cbd0308fbc)","logger_name":"com.selise.inb.automation.auth.UserContext","thread_name":"main","level":"INFO","level_value":20000,"application":"selise-automation"}
{"@timestamp":"2026-01-04T00:17:25.195189+06:00","@version":"1","message":"Authenticated as: Xiao Doe | Organization: c3c8a454-9530-41ba-8a43-c4cbd0308fbc","logger_name":"com.selise.inb.automation.auth.AuthenticationHelper","thread_name":"main","level":"INFO","level_value":20000,"application":"selise-automation"}
{"@timestamp":"2026-01-04T00:17:25.201172+06:00","@version":"1","message":"BackendAutomationAPIService initialized with token-based authentication","logger_name":"com.selise.inb.automation.api.BackendAutomationAPIService","thread_name":"main","level":"INFO","level_value":20000,"application":"selise-automation"}
{"@timestamp":"2026-01-04T00:17:25.2021885+06:00","@version":"1","message":"Retrieving API test plan for organization: c3c8a454-9530-41ba-8a43-c4cbd0308fbc and environment: CRUDTest","logger_name":"com.selise.inb.automation.api.BackendAutomationAPIService","thread_name":"main","level":"INFO","level_value":20000,"application":"selise-automation"}
{"@timestamp":"2026-01-04T00:17:25.2293899+06:00","@version":"1","message":"Response Code: 200","logger_name":"com.selise.inb.automation.api.BackendAutomationAPIService","thread_name":"main","level":"INFO","level_value":20000,"application":"selise-automation"}
{"@timestamp":"2026-01-04T00:17:25.2452575+06:00","@version":"1","message":"Retrieved 12 API test plans from API","logger_name":"com.selise.inb.automation.api.BackendAutomationAPIService","thread_name":"main","level":"INFO","level_value":20000,"application":"selise-automation"}
{"@timestamp":"2026-01-04T00:17:25.2482107+06:00","@version":"1","message":"Found API test plan for environment: CRUDTest","logger_name":"com.selise.inb.automation.api.BackendAutomationAPIService","thread_name":"main","level":"INFO","level_value":20000,"application":"selise-automation"}
{"@timestamp":"2026-01-04T00:17:25.2492096+06:00","@version":"1","message":"Retrieved API test plan: 50f6c956-3817-4473-b35b-4d682f423504","logger_name":"com.selise.inb.application.BackendAutomationRunner","thread_name":"main","level":"INFO","level_value":20000,"application":"selise-automation"}
{"@timestamp":"2026-01-04T00:17:25.2502121+06:00","@version":"1","message":"Fetching global variables for test plan ID: 50f6c956-3817-4473-b35b-4d682f423504 (Organization: c3c8a454-9530-41ba-8a43-c4cbd0308fbc)","logger_name":"com.selise.inb.automation.api.BackendAutomationAPIService","thread_name":"main","level":"INFO","level_value":20000,"application":"selise-automation"}
{"@timestamp":"2026-01-04T00:17:25.2698565+06:00","@version":"1","message":"GlobalVariables API Response Code: 200 for organization: c3c8a454-9530-41ba-8a43-c4cbd0308fbc","logger_name":"com.selise.inb.automation.api.BackendAutomationAPIService","thread_name":"main","level":"INFO","level_value":20000,"application":"selise-automation"}
{"@timestamp":"2026-01-04T00:17:25.2737597+06:00","@version":"1","message":"Could not retrieve global variables for test plan '50f6c956-3817-4473-b35b-4d682f423504' (Organization: 'c3c8a454-9530-41ba-8a43-c4cbd0308fbc'): JSONObject[\"Data\"] is not a JSONObject (class org.json.JSONArray).. Automation will continue.","logger_name":"com.selise.inb.automation.api.BackendAutomationAPIService","thread_name":"main","level":"WARN","level_value":30000,"application":"selise-automation"}
{"@timestamp":"2026-01-04T00:17:25.2747622+06:00","@version":"1","message":"ℹ No global variables for this test plan (automation will proceed normally)","logger_name":"com.selise.inb.application.BackendAutomationRunner","thread_name":"main","level":"INFO","level_value":20000,"application":"selise-automation"}
{"@timestamp":"2026-01-04T00:17:25.2747622+06:00","@version":"1","message":"Retrieving API test suites for test plan ID: 50f6c956-3817-4473-b35b-4d682f423504 and organization ID: c3c8a454-9530-41ba-8a43-c4cbd0308fbc","logger_name":"com.selise.inb.automation.api.BackendAutomationAPIService","thread_name":"main","level":"INFO","level_value":20000,"application":"selise-automation"}
{"@timestamp":"2026-01-04T00:17:25.300768+06:00","@version":"1","message":"Response Code: 200","logger_name":"com.selise.inb.automation.api.BackendAutomationAPIService","thread_name":"main","level":"INFO","level_value":20000,"application":"selise-automation"}
{"@timestamp":"2026-01-04T00:17:25.3072093+06:00","@version":"1","message":"Retrieved 12 API test suites from API","logger_name":"com.selise.inb.automation.api.BackendAutomationAPIService","thread_name":"main","level":"INFO","level_value":20000,"application":"selise-automation"}
{"@timestamp":"2026-01-04T00:17:25.377011+06:00","@version":"1","message":"[KAFKA] Parsed action 'test': ActionType=KAFKA, CustomCode=, Operation=CONSUME_VERIFY","logger_name":"com.selise.inb.automation.api.BackendAutomationAPIService","thread_name":"ForkJoinPool.commonPool-worker-1","level":"INFO","level_value":20000,"application":"selise-automation"}
{"@timestamp":"2026-01-04T00:17:25.3850385+06:00","@version":"1","message":"Found 1 API test suites for test plan ID: 50f6c956-3817-4473-b35b-4d682f423504","logger_name":"com.selise.inb.automation.api.BackendAutomationAPIService","thread_name":"main","level":"INFO","level_value":20000,"application":"selise-automation"}
{"@timestamp":"2026-01-04T00:17:25.3860682+06:00","@version":"1","message":"Found 1 API test suites for execution","logger_name":"com.selise.inb.application.BackendAutomationRunner","thread_name":"main","level":"INFO","level_value":20000,"application":"selise-automation"}
{"@timestamp":"2026-01-04T00:17:25.3930368+06:00","@version":"1","message":"API report will be generated at: Reports/04012026_Demo_CRUDTest_001725_API_AutomationReport.html","logger_name":"com.selise.inb.automation.utils.ApiReportingUtils","thread_name":"main","level":"INFO","level_value":20000,"application":"selise-automation"}
{"@timestamp":"2026-01-04T00:17:25.7570819+06:00","@version":"1","message":"BackendAutomationAPIService initialized with token-based authentication","logger_name":"com.selise.inb.automation.api.BackendAutomationAPIService","thread_name":"main","level":"INFO","level_value":20000,"application":"selise-automation"}
{"@timestamp":"2026-01-04T00:17:27.6475529+06:00","@version":"1","message":"RestAssured has been statically configured to relax HTTPS validation and enable content decoding.","logger_name":"com.selise.inb.automation.handlers.ApiActionExecutor","thread_name":"main","level":"INFO","level_value":20000,"application":"selise-automation"}
{"@timestamp":"2026-01-04T00:17:27.6616123+06:00","@version":"1","message":"ApiTestSuiteExecutor initialized successfully for API automation","logger_name":"com.selise.inb.automation.services.ApiTestSuiteExecutor","thread_name":"main","level":"INFO","level_value":20000,"application":"selise-automation"}
{"@timestamp":"2026-01-04T00:17:27.7147316+06:00","@version":"1","message":"[API] Starting API Action: 1. Create New Post","logger_name":"com.selise.inb.automation.utils.ApiReportingUtils","thread_name":"main","level":"INFO","level_value":20000,"application":"selise-automation"}
{"@timestamp":"2026-01-04T00:17:27.7167286+06:00","@version":"1","message":"[HYBRID] Executing 1. Create New Post action: API","logger_name":"com.selise.inb.automation.handlers.ApiActionExecutor","thread_name":"main","level":"INFO","level_value":20000,"application":"selise-automation"}
{"@timestamp":"2026-01-04T00:17:27.7187301+06:00","@version":"1","message":"[API] Starting API Action: 1. Create New Post","logger_name":"com.selise.inb.automation.handlers.ApiActionExecutor","thread_name":"main","level":"INFO","level_value":20000,"application":"selise-automation"}
{"@timestamp":"2026-01-04T00:17:28.1406843+06:00","@version":"1","message":"[API] Request Method: POST","logger_name":"com.selise.inb.automation.handlers.ApiActionExecutor","thread_name":"main","level":"INFO","level_value":20000,"application":"selise-automation"}
{"@timestamp":"2026-01-04T00:17:28.1416838+06:00","@version":"1","message":"[API] Request URL: https://683d6eb6199a0039e9e56e4a.mockapi.io/api/v1/posts","logger_name":"com.selise.inb.automation.handlers.ApiActionExecutor","thread_name":"main","level":"INFO","level_value":20000,"application":"selise-automation"}
{"@timestamp":"2026-01-04T00:17:28.1426752+06:00","@version":"1","message":"[API] Request Headers: {Accept=application/json, Content-Type=application/json; charset=UTF-8}","logger_name":"com.selise.inb.automation.handlers.ApiActionExecutor","thread_name":"main","level":"INFO","level_value":20000,"application":"selise-automation"}
{"@timestamp":"2026-01-04T00:17:28.1436955+06:00","@version":"1","message":"[API] Request Body: {\"userId\": 55, \"title\": \"My Test Post via Automation\",\"body\": \"This content is generated by the INB Automation Tool.\",\"status\": \"draft\",\"tags\": [\"automation\", \"poc\", \"testing\"],\"isFeatured\": false, \"viewCount\": 0}","logger_name":"com.selise.inb.automation.handlers.ApiActionExecutor","thread_name":"main","level":"INFO","level_value":20000,"application":"selise-automation"}
{"@timestamp":"2026-01-04T00:17:31.44226+06:00","@version":"1","message":"[API] Response Headers: Access-Control-Allow-Headers=X-Requested-With,Content-Type,Cache-Control,access_token\nAccess-Control-Allow-Methods=GET,PUT,POST,DELETE,OPTIONS\nAccess-Control-Allow-Origin=*\nContent-Length=251\nContent-Type=application/json\nDate=Sat, 03 Jan 2026 18:17:28 GMT\nNel={\"report_to\":\"heroku-nel\",\"response_headers\":[\"Via\"],\"max_age\":3600,\"success_fraction\":0.01,\"failure_fraction\":0.1}\nReport-To={\"group\":\"heroku-nel\",\"endpoints\":[{\"url\":\"https://nel.heroku.com/reports?s=MXpzIehEg6KLy8ARs9YvLDYQY3e6gDK6P295KkbRv1M%3D\\u0026sid=1b10b0ff-8a76-4548-befa-353fc6c6c045\\u0026ts=1767464248\"}],\"max_age\":3600}\nReporting-Endpoints=heroku-nel=\"https://nel.heroku.com/reports?s=MXpzIehEg6KLy8ARs9YvLDYQY3e6gDK6P295KkbRv1M%3D&sid=1b10b0ff-8a76-4548-befa-353fc6c6c045&ts=1767464248\"\nServer=Heroku\nVia=1.1 heroku-router\nX-Powered-By=Express","logger_name":"com.selise.inb.automation.handlers.ApiActionExecutor","thread_name":"main","level":"INFO","level_value":20000,"application":"selise-automation"}
{"@timestamp":"2026-01-04T00:17:31.4432641+06:00","@version":"1","message":"[API] Response Content-Type: application/json","logger_name":"com.selise.inb.automation.handlers.ApiActionExecutor","thread_name":"main","level":"INFO","level_value":20000,"application":"selise-automation"}
{"@timestamp":"2026-01-04T00:17:31.4553905+06:00","@version":"1","message":"[API] Response FirstBytesHex: 7B 22 63 72 65 61 74 65 64 41 74 22 3A 22 32 30 ...","logger_name":"com.selise.inb.automation.handlers.ApiActionExecutor","thread_name":"main","level":"INFO","level_value":20000,"application":"selise-automation"}
{"@timestamp":"2026-01-04T00:17:31.4654043+06:00","@version":"1","message":"[API] Response Status Code: 201","logger_name":"com.selise.inb.automation.utils.ApiReportingUtils","thread_name":"main","level":"INFO","level_value":20000,"application":"selise-automation"}
{"@timestamp":"2026-01-04T00:17:31.4654043+06:00","@version":"1","message":"[API] Response Time: 3297 ms","logger_name":"com.selise.inb.automation.utils.ApiReportingUtils","thread_name":"main","level":"INFO","level_value":20000,"application":"selise-automation"}
{"@timestamp":"2026-01-04T00:17:31.4663926+06:00","@version":"1","message":"[API] Response Body: {\"createdAt\":\"2026-01-03T12:40:17.176Z\",\"userId\":55,\"title\":\"My Test Post via Automation\",\"body\":\"This content is generated by the INB Automation Tool.\",\"status\":\"draft\",\"tags\":[\"automation\",\"poc\",\"testing\"],\"isFeatured\":false,\"viewCount\":0,\"id\":\"36\"}","logger_name":"com.selise.inb.automation.utils.ApiReportingUtils","thread_name":"main","level":"INFO","level_value":20000,"application":"selise-automation"}
{"@timestamp":"2026-01-04T00:17:31.475396+06:00","@version":"1","message":"[API] SUCCESS: Assertion PASSED. Actual: 201","logger_name":"com.selise.inb.automation.utils.ApiReportingUtils","thread_name":"main","level":"INFO","level_value":20000,"application":"selise-automation"}
{"@timestamp":"2026-01-04T00:17:32.4837355+06:00","@version":"1","message":"[API] SUCCESS: Assertion PASSED. Actual: My Test Post via Automation","logger_name":"com.selise.inb.automation.utils.ApiReportingUtils","thread_name":"main","level":"INFO","level_value":20000,"application":"selise-automation"}
{"@timestamp":"2026-01-04T00:17:32.5247357+06:00","@version":"1","message":"[API] SUCCESS: Assertion PASSED. Actual: 36","logger_name":"com.selise.inb.automation.utils.ApiReportingUtils","thread_name":"main","level":"INFO","level_value":20000,"application":"selise-automation"}
{"@timestamp":"2026-01-04T00:17:32.5557623+06:00","@version":"1","message":"[API] SUCCESS: Assertion PASSED. Actual: 55","logger_name":"com.selise.inb.automation.utils.ApiReportingUtils","thread_name":"main","level":"INFO","level_value":20000,"application":"selise-automation"}
{"@timestamp":"2026-01-04T00:17:32.6285298+06:00","@version":"1","message":"[API] Captured variable 'newPostTitle' with path 'title' resulted in value: My Test Post via Automation","logger_name":"com.selise.inb.automation.handlers.ApiActionExecutor","thread_name":"main","level":"INFO","level_value":20000,"application":"selise-automation"}
{"@timestamp":"2026-01-04T00:17:32.6295273+06:00","@version":"1","message":"[API] Captured variable 'newPostId' with path 'id' resulted in value: 36","logger_name":"com.selise.inb.automation.handlers.ApiActionExecutor","thread_name":"main","level":"INFO","level_value":20000,"application":"selise-automation"}
{"@timestamp":"2026-01-04T00:17:32.6295273+06:00","@version":"1","message":"[API] SUCCESS: API Action '1. Create New Post' PASSED.","logger_name":"com.selise.inb.automation.utils.ApiReportingUtils","thread_name":"main","level":"INFO","level_value":20000,"application":"selise-automation"}
{"@timestamp":"2026-01-04T00:17:32.6315274+06:00","@version":"1","message":"[API] Starting API Action: test","logger_name":"com.selise.inb.automation.utils.ApiReportingUtils","thread_name":"main","level":"INFO","level_value":20000,"application":"selise-automation"}
{"@timestamp":"2026-01-04T00:17:32.6315274+06:00","@version":"1","message":"[HYBRID] Executing test action: KAFKA","logger_name":"com.selise.inb.automation.handlers.ApiActionExecutor","thread_name":"main","level":"INFO","level_value":20000,"application":"selise-automation"}
{"@timestamp":"2026-01-04T00:17:32.6325287+06:00","@version":"1","message":"[SAF-KAFKA] [EXEC] Starting Kafka action | action=test","logger_name":"com.selise.inb.automation.handlers.KafkaActionExecutor","thread_name":"main","level":"INFO","level_value":20000,"application":"selise-automation"}
{"@timestamp":"2026-01-04T00:17:32.6386346+06:00","@version":"1","message":"Failed to consume and verify message: null","logger_name":"com.selise.inb.automation.handlers.KafkaActionExecutor","thread_name":"main","level":"ERROR","level_value":40000,"stack_trace":"java.lang.NullPointerException: null\r\n\tat java.base/java.util.concurrent.ConcurrentHashMap.putVal(ConcurrentHashMap.java:1011)\r\n\tat java.base/java.util.concurrent.ConcurrentHashMap.put(ConcurrentHashMap.java:1006)\r\n\tat java.base/java.util.Properties.put(Properties.java:1346)\r\n\tat com.selise.inb.automation.handlers.KafkaActionExecutor.applySecurityConfig(KafkaActionExecutor.java:1879)\r\n\tat com.selise.inb.automation.handlers.KafkaActionExecutor.getOrCreateConsumer(KafkaActionExecutor.java:1850)\r\n\tat com.selise.inb.automation.handlers.KafkaActionExecutor.consumeAndVerify(KafkaActionExecutor.java:821)\r\n\tat com.selise.inb.automation.handlers.KafkaActionExecutor.executeStandardKafkaOperation(KafkaActionExecutor.java:314)\r\n\tat com.selise.inb.automation.handlers.KafkaActionExecutor.executeKafkaAction(KafkaActionExecutor.java:286)\r\n\tat com.selise.inb.automation.handlers.ApiActionExecutor.executeAction(ApiActionExecutor.java:202)\r\n\tat com.selise.inb.automation.handlers.ApiExecutionHandler.executeApiActions(ApiExecutionHandler.java:167)\r\n\tat com.selise.inb.automation.handlers.ApiExecutionHandler.lambda$executeApiTestSuites$0(ApiExecutionHandler.java:116)\r\n\tat java.base/java.util.ArrayList.forEach(ArrayList.java:1596)\r\n\tat com.selise.inb.automation.handlers.ApiExecutionHandler.executeApiTestSuites(ApiExecutionHandler.java:101)\r\n\tat com.selise.inb.automation.services.ApiTestSuiteExecutor.execute(ApiTestSuiteExecutor.java:55)\r\n\tat com.selise.inb.application.BackendAutomationRunner.main(BackendAutomationRunner.java:98)\r\n\tat com.selise.inb.application.InbAutomationApp.main(InbAutomationApp.java:40)\r\n","application":"selise-automation"}
{"@timestamp":"2026-01-04T00:17:32.6445071+06:00","@version":"1","message":"[API] FAILURE: API Action 'test' FAILED: Action failed validation","logger_name":"com.selise.inb.automation.utils.ApiReportingUtils","thread_name":"main","level":"ERROR","level_value":40000,"application":"selise-automation"}
{"@timestamp":"2026-01-04T00:17:32.6455592+06:00","@version":"1","message":"[API] Starting API Action: fgfg","logger_name":"com.selise.inb.automation.utils.ApiReportingUtils","thread_name":"main","level":"INFO","level_value":20000,"application":"selise-automation"}
{"@timestamp":"2026-01-04T00:17:32.6465756+06:00","@version":"1","message":"[HYBRID] Executing fgfg action: API","logger_name":"com.selise.inb.automation.handlers.ApiActionExecutor","thread_name":"main","level":"INFO","level_value":20000,"application":"selise-automation"}
{"@timestamp":"2026-01-04T00:17:32.6465756+06:00","@version":"1","message":"[API] Starting API Action: fgfg","logger_name":"com.selise.inb.automation.handlers.ApiActionExecutor","thread_name":"main","level":"INFO","level_value":20000,"application":"selise-automation"}
{"@timestamp":"2026-01-04T00:17:32.6485237+06:00","@version":"1","message":"[API] Request Method: GET","logger_name":"com.selise.inb.automation.handlers.ApiActionExecutor","thread_name":"main","level":"INFO","level_value":20000,"application":"selise-automation"}
{"@timestamp":"2026-01-04T00:17:32.6485237+06:00","@version":"1","message":"[API] Request URL: gfgfg","logger_name":"com.selise.inb.automation.handlers.ApiActionExecutor","thread_name":"main","level":"INFO","level_value":20000,"application":"selise-automation"}
{"@timestamp":"2026-01-04T00:17:32.6505478+06:00","@version":"1","message":"[API] Request Headers: {}","logger_name":"com.selise.inb.automation.handlers.ApiActionExecutor","thread_name":"main","level":"INFO","level_value":20000,"application":"selise-automation"}
{"@timestamp":"2026-01-04T00:17:32.6515469+06:00","@version":"1","message":"[API] Request Body: fgfg","logger_name":"com.selise.inb.automation.handlers.ApiActionExecutor","thread_name":"main","level":"INFO","level_value":20000,"application":"selise-automation"}
{"@timestamp":"2026-01-04T00:17:32.728402+06:00","@version":"1","message":"Error during API request: Connection refused: connect","logger_name":"com.selise.inb.automation.handlers.ApiActionExecutor","thread_name":"main","level":"ERROR","level_value":40000,"stack_trace":"java.net.ConnectException: Connection refused: connect\r\n\tat java.base/sun.nio.ch.Net.connect0(Native Method)\r\n\tat java.base/sun.nio.ch.Net.connect(Net.java:589)\r\n\tat java.base/sun.nio.ch.Net.connect(Net.java:578)\r\n\tat java.base/sun.nio.ch.NioSocketImpl.connect(NioSocketImpl.java:583)\r\n\tat java.base/java.net.SocksSocketImpl.connect(SocksSocketImpl.java:327)\r\n\tat java.base/java.net.Socket.connect(Socket.java:751)\r\n\tat org.apache.http.conn.scheme.PlainSocketFactory.connectSocket(PlainSocketFactory.java:121)\r\n\tat org.apache.http.impl.conn.DefaultClientConnectionOperator.openConnection(DefaultClientConnectionOperator.java:180)\r\n\tat org.apache.http.impl.conn.ManagedClientConnectionImpl.open(ManagedClientConnectionImpl.java:326)\r\n\tat org.apache.http.impl.client.DefaultRequestDirector.tryConnect(DefaultRequestDirector.java:605)\r\n\tat org.apache.http.impl.client.DefaultRequestDirector.execute(DefaultRequestDirector.java:440)\r\n\tat org.apache.http.impl.client.AbstractHttpClient.doExecute(AbstractHttpClient.java:835)\r\n\tat org.apache.http.impl.client.CloseableHttpClient.execute(CloseableHttpClient.java:83)\r\n\tat io.restassured.internal.RestAssuredHttpBuilder.doRequest(RestAssuredHttpBuilder.java:141)\r\n\tat io.restassured.internal.http.HTTPBuilder.doRequest(HTTPBuilder.java:496)\r\n\tat io.restassured.internal.http.HTTPBuilder.request(HTTPBuilder.java:453)\r\n\tat io.restassured.internal.http.HTTPBuilder$request$3.call(Unknown Source)\r\n\tat org.codehaus.groovy.runtime.callsite.CallSiteArray.defaultCall(CallSiteArray.java:45)\r\n\tat org.codehaus.groovy.runtime.callsite.AbstractCallSite.call(AbstractCallSite.java:125)\r\n\tat org.codehaus.groovy.runtime.callsite.AbstractCallSite.call(AbstractCallSite.java:166)\r\n\tat io.restassured.internal.RequestSpecificationImpl.sendHttpRequest(RequestSpecificationImpl.groovy:1480)\r\n\tat io.restassured.internal.RequestSpecificationImpl.this$2$sendHttpRequest(RequestSpecificationImpl.groovy)\r\n\tat java.base/jdk.internal.reflect.DirectMethodHandleAccessor.invoke(DirectMethodHandleAccessor.java:103)\r\n\tat java.base/java.lang.reflect.Method.invoke(Method.java:580)\r\n\tat org.codehaus.groovy.reflection.CachedMethod.invoke(CachedMethod.java:343)\r\n\tat groovy.lang.MetaMethod.doMethodInvoke(MetaMethod.java:328)\r\n\tat groovy.lang.MetaClassImpl.doInvokeMethod(MetaClassImpl.java:1333)\r\n\tat groovy.lang.MetaClassImpl.invokeMethod(MetaClassImpl.java:1088)\r\n\tat groovy.lang.MetaClassImpl.invokeMethod(MetaClassImpl.java:1007)\r\n\tat groovy.lang.MetaClassImpl.invokeMethod(MetaClassImpl.java:790)\r\n\tat io.restassured.internal.RequestSpecificationImpl.invokeMethod(RequestSpecificationImpl.groovy)\r\n\tat org.codehaus.groovy.runtime.callsite.PogoInterceptableSite.call(PogoInterceptableSite.java:46)\r\n\tat org.codehaus.groovy.runtime.callsite.PogoInterceptableSite.callCurrent(PogoInterceptableSite.java:57)\r\n\tat org.codehaus.groovy.runtime.callsite.CallSiteArray.defaultCallCurrent(CallSiteArray.java:49)\r\n\tat org.codehaus.groovy.runtime.callsite.AbstractCallSite.callCurrent(AbstractCallSite.java:171)\r\n\tat io.restassured.internal.RequestSpecificationImpl.sendRequest(RequestSpecificationImpl.groovy:1229)\r\n\tat io.restassured.internal.RequestSpecificationImpl.this$2$sendRequest(RequestSpecificationImpl.groovy)\r\n\tat java.base/jdk.internal.reflect.DirectMethodHandleAccessor.invoke(DirectMethodHandleAccessor.java:103)\r\n\tat java.base/java.lang.reflect.Method.invoke(Method.java:580)\r\n\tat org.codehaus.groovy.reflection.CachedMethod.invoke(CachedMethod.java:343)\r\n\tat groovy.lang.MetaMethod.doMethodInvoke(MetaMethod.java:328)\r\n\tat groovy.lang.MetaClassImpl.doInvokeMethod(MetaClassImpl.java:1333)\r\n\tat groovy.lang.MetaClassImpl.invokeMethod(MetaClassImpl.java:1088)\r\n\tat groovy.lang.MetaClassImpl.invokeMethod(MetaClassImpl.java:1007)\r\n\tat groovy.lang.MetaClassImpl.invokeMethod(MetaClassImpl.java:790)\r\n\tat io.restassured.internal.RequestSpecificationImpl.invokeMethod(RequestSpecificationImpl.groovy)\r\n\tat org.codehaus.groovy.runtime.callsite.PogoInterceptableSite.call(PogoInterceptableSite.java:46)\r\n\tat org.codehaus.groovy.runtime.callsite.AbstractCallSite.call(AbstractCallSite.java:166)\r\n\tat io.restassured.internal.filter.SendRequestFilter.filter(SendRequestFilter.groovy:30)\r\n\tat io.restassured.filter.Filter$filter$0.call(Unknown Source)\r\n\tat org.codehaus.groovy.runtime.callsite.CallSiteArray.defaultCall(CallSiteArray.java:45)\r\n\tat io.restassured.filter.Filter$filter.call(Unknown Source)\r\n\tat io.restassured.internal.filter.FilterContextImpl.next(FilterContextImpl.groovy:72)\r\n\tat io.restassured.filter.time.TimingFilter.filter(TimingFilter.java:56)\r\n\tat io.restassured.filter.Filter$filter.call(Unknown Source)\r\n\tat org.codehaus.groovy.runtime.callsite.CallSiteArray.defaultCall(CallSiteArray.java:45)\r\n\tat io.restassured.filter.Filter$filter$0.call(Unknown Source)\r\n\tat io.restassured.internal.filter.FilterContextImpl.next(FilterContextImpl.groovy:72)\r\n\tat io.restassured.filter.FilterContext$next.call(Unknown Source)\r\n\tat io.restassured.internal.filter.CsrfFilter.filter(CsrfFilter.groovy:89)\r\n\tat io.restassured.filter.Filter$filter$0.call(Unknown Source)\r\n\tat org.codehaus.groovy.runtime.callsite.CallSiteArray.defaultCall(CallSiteArray.java:45)\r\n\tat io.restassured.filter.Filter$filter.call(Unknown Source)\r\n\tat io.restassured.internal.filter.FilterContextImpl.next(FilterContextImpl.groovy:72)\r\n\tat io.restassured.filter.log.RequestLoggingFilter.filter(RequestLoggingFilter.java:148)\r\n\tat io.restassured.filter.Filter$filter.call(Unknown Source)\r\n\tat org.codehaus.groovy.runtime.callsite.CallSiteArray.defaultCall(CallSiteArray.java:45)\r\n\tat io.restassured.filter.Filter$filter$0.call(Unknown Source)\r\n\tat io.restassured.internal.filter.FilterContextImpl.next(FilterContextImpl.groovy:72)\r\n\tat io.restassured.filter.FilterContext$next.call(Unknown Source)\r\n\tat io.restassured.internal.RequestSpecificationImpl.applyPathParamsAndSendRequest(RequestSpecificationImpl.groovy:1704)\r\n\tat io.restassured.internal.RequestSpecificationImpl.this$2$applyPathParamsAndSendRequest(RequestSpecificationImpl.groovy)\r\n\tat java.base/jdk.internal.reflect.DirectMethodHandleAccessor.invoke(DirectMethodHandleAccessor.java:103)\r\n\tat java.base/java.lang.reflect.Method.invoke(Method.java:580)\r\n\tat org.codehaus.groovy.reflection.CachedMethod.invoke(CachedMethod.java:343)\r\n\tat groovy.lang.MetaMethod.doMethodInvoke(MetaMethod.java:328)\r\n\tat groovy.lang.MetaClassImpl.doInvokeMethod(MetaClassImpl.java:1333)\r\n\tat groovy.lang.MetaClassImpl.invokeMethod(MetaClassImpl.java:1088)\r\n\tat groovy.lang.MetaClassImpl.invokeMethod(MetaClassImpl.java:1007)\r\n\tat groovy.lang.MetaClassImpl.invokeMethod(MetaClassImpl.java:790)\r\n\tat io.restassured.internal.RequestSpecificationImpl.invokeMethod(RequestSpecificationImpl.groovy)\r\n\tat org.codehaus.groovy.runtime.callsite.PogoInterceptableSite.call(PogoInterceptableSite.java:46)\r\n\tat org.codehaus.groovy.runtime.callsite.PogoInterceptableSite.callCurrent(PogoInterceptableSite.java:57)\r\n\tat org.codehaus.groovy.runtime.callsite.AbstractCallSite.callCurrent(AbstractCallSite.java:203)\r\n\tat io.restassured.internal.RequestSpecificationImpl.applyPathParamsAndSendRequest(RequestSpecificationImpl.groovy:1710)\r\n\tat io.restassured.internal.RequestSpecificationImpl.this$2$applyPathParamsAndSendRequest(RequestSpecificationImpl.groovy)\r\n\tat java.base/jdk.internal.reflect.DirectMethodHandleAccessor.invoke(DirectMethodHandleAccessor.java:103)\r\n\tat java.base/java.lang.reflect.Method.invoke(Method.java:580)\r\n\tat org.codehaus.groovy.reflection.CachedMethod.invoke(CachedMethod.java:343)\r\n\tat groovy.lang.MetaMethod.doMethodInvoke(MetaMethod.java:328)\r\n\tat groovy.lang.MetaClassImpl.doInvokeMethod(MetaClassImpl.java:1333)\r\n\tat groovy.lang.MetaClassImpl.invokeMethod(MetaClassImpl.java:1088)\r\n\tat groovy.lang.MetaClassImpl.invokeMethod(MetaClassImpl.java:1007)\r\n\tat groovy.lang.MetaClassImpl.invokeMethod(MetaClassImpl.java:790)\r\n\tat io.restassured.internal.RequestSpecificationImpl.invokeMethod(RequestSpecificationImpl.groovy)\r\n\tat org.codehaus.groovy.runtime.callsite.PogoInterceptableSite.call(PogoInterceptableSite.java:46)\r\n\tat org.codehaus.groovy.runtime.callsite.PogoInterceptableSite.callCurrent(PogoInterceptableSite.java:57)\r\n\tat org.codehaus.groovy.runtime.callsite.CallSiteArray.defaultCallCurrent(CallSiteArray.java:49)\r\n\tat org.codehaus.groovy.runtime.callsite.AbstractCallSite.callCurrent(AbstractCallSite.java:171)\r\n\tat org.codehaus.groovy.runtime.callsite.AbstractCallSite.callCurrent(AbstractCallSite.java:203)\r\n\tat io.restassured.internal.RequestSpecificationImpl.get(RequestSpecificationImpl.groovy:172)\r\n\tat io.restassured.internal.RequestSpecificationImpl.get(RequestSpecificationImpl.groovy)\r\n\tat com.selise.inb.automation.handlers.ApiActionExecutor.executeApiAction(ApiActionExecutor.java:284)\r\n\tat com.selise.inb.automation.handlers.ApiActionExecutor.executeAction(ApiActionExecutor.java:210)\r\n\tat com.selise.inb.automation.handlers.ApiExecutionHandler.executeApiActions(ApiExecutionHandler.java:167)\r\n\tat com.selise.inb.automation.handlers.ApiExecutionHandler.lambda$executeApiTestSuites$0(ApiExecutionHandler.java:116)\r\n\tat java.base/java.util.ArrayList.forEach(ArrayList.java:1596)\r\n\tat com.selise.inb.automation.handlers.ApiExecutionHandler.executeApiTestSuites(ApiExecutionHandler.java:101)\r\n\tat com.selise.inb.automation.services.ApiTestSuiteExecutor.execute(ApiTestSuiteExecutor.java:55)\r\n\tat com.selise.inb.application.BackendAutomationRunner.main(BackendAutomationRunner.java:98)\r\n\tat com.selise.inb.application.InbAutomationApp.main(InbAutomationApp.java:40)\r\n","application":"selise-automation"}
{"@timestamp":"2026-01-04T00:17:32.7333879+06:00","@version":"1","message":"[API] FAILURE: API Action 'fgfg' FAILED: Action failed validation","logger_name":"com.selise.inb.automation.utils.ApiReportingUtils","thread_name":"main","level":"ERROR","level_value":40000,"application":"selise-automation"}
{"@timestamp":"2026-01-04T00:17:32.734285+06:00","@version":"1","message":"[CROSS-SUITE] Suite 'CRUD API Test' captured 2 new variables (total: 2)","logger_name":"com.selise.inb.automation.handlers.ApiExecutionHandler","thread_name":"main","level":"INFO","level_value":20000,"application":"selise-automation"}
{"@timestamp":"2026-01-04T00:17:32.7353838+06:00","@version":"1","message":"Total API Execution Time: 5 seconds","logger_name":"com.selise.inb.automation.handlers.ApiExecutionHandler","thread_name":"main","level":"INFO","level_value":20000,"application":"selise-automation"}
{"@timestamp":"2026-01-04T00:17:33.3105926+06:00","@version":"1","message":"API test execution completed. Report generated successfully.","logger_name":"com.selise.inb.automation.handlers.ApiExecutionHandler","thread_name":"main","level":"INFO","level_value":20000,"application":"selise-automation"}
{"@timestamp":"2026-01-04T00:17:33.3116067+06:00","@version":"1","message":"Sending API report to cloud app with test plan ID: 50f6c956-3817-4473-b35b-4d682f423504","logger_name":"com.selise.inb.automation.handlers.ApiExecutionHandler","thread_name":"main","level":"INFO","level_value":20000,"application":"selise-automation"}
{"@timestamp":"2026-01-04T00:17:33.4396453+06:00","@version":"1","message":"Response Code: 200","logger_name":"com.selise.inb.automation.api.BackendAutomationAPIService","thread_name":"main","level":"INFO","level_value":20000,"application":"selise-automation"}
{"@timestamp":"2026-01-04T00:17:33.44565+06:00","@version":"1","message":"API report sent successfully. Report Name: 04012026_Demo_CRUDTest_001725_API_AutomationReport.html","logger_name":"com.selise.inb.automation.api.BackendAutomationAPIService","thread_name":"main","level":"INFO","level_value":20000,"application":"selise-automation"}
{"@timestamp":"2026-01-04T00:17:33.4466739+06:00","@version":"1","message":"API report sent to cloud app successfully","logger_name":"com.selise.inb.automation.handlers.ApiExecutionHandler","thread_name":"main","level":"INFO","level_value":20000,"application":"selise-automation"}
{"@timestamp":"2026-01-04T00:17:34.4581059+06:00","@version":"1","message":"Backend Automation Completed","logger_name":"com.selise.inb.application.BackendAutomationRunner","thread_name":"main","level":"INFO","level_value":20000,"application":"selise-automation"}
